textutils/__init__.py
textutils/checker.py
textutils/counter.py
textutils/formatter.py
textutils_jahnvi-1.0.0.dist-info/METADATA
textutils_jahnvi-1.0.0.dist-info/WHEEL
textutils_jahnvi-1.0.0.dist-info/top_level.txt
textutils_jahnvi-1.0.0.dist-info/RECORD
