Metadata-Version: 2.4
Name: textutils-jahnvi
Version: 1.0.0
Summary: Text utility library for counting, formatting and checking text
Author: Jahnvi Goyal
Dynamic: author
Dynamic: summary
